iso_language_codes/__init__.py
iso_language_codes/iso_language_codes.py
iso_language_codes/language_codes.db.bak
iso_language_codes/language_codes.db.dat
iso_language_codes/language_codes.db.dir
iso_language_codes-1.1.0.dist-info/LICENSE
iso_language_codes-1.1.0.dist-info/METADATA
iso_language_codes-1.1.0.dist-info/WHEEL
iso_language_codes-1.1.0.dist-info/top_level.txt
iso_language_codes-1.1.0.dist-info/RECORD
