Metadata-Version: 2.1
Name: iso-language-codes
Version: 1.1.0
Summary: Get ISO code for a given language
Home-page: https://github.com/kirinokirino/iso_language_codes
Author: Andrei Ruzin
Author-email: kirinokirino2501@gmail.com
License: MIT license
Keywords: iso_language_codes
Platform: UNKNOWN
Classifier: Development Status :: 2 - Pre-Alpha
Classifier: License :: OSI Approved :: MIT License
Classifier: Programming Language :: Python :: 3
Classifier: Programming Language :: Python :: 3.6
Classifier: Programming Language :: Python :: 3.7
